sankaku/__init__.py
sankaku/client.py
sankaku/lib/__init__.py
sankaku/lib/headers.py
sankaku/lib/objects.py
Sankaku.py-1.0.0.dist-info/LICENSE
Sankaku.py-1.0.0.dist-info/METADATA
Sankaku.py-1.0.0.dist-info/WHEEL
Sankaku.py-1.0.0.dist-info/top_level.txt
Sankaku.py-1.0.0.dist-info/RECORD
