Metadata-Version: 2.1
Name: Sankaku.py
Version: 1.0.0
Summary: A library to create Sankaku Complex bots.
Home-page: https://github.com/Slimakoi/Sankaku.py
Author: Slimakoi
Author-email: slimeytoficial@gmail.com
License: MIT
Download-URL: https://github.com/Slimakoi/Sankaku.py/tarball/master
Keywords: sankaku,sankaku-complex,sankaku-py,sankaku-bot,api,python,python3,python3.x,slimakoi,official
Platform: UNKNOWN
License-File: LICENSE
Requires-Dist: setuptools
Requires-Dist: requests
Requires-Dist: six
